{
    "Name": "IoTHubInput",
    "Type": "Data Stream",
    "DataSourceType": "IoT Hub",
    "IoTHubProperties": {
        "IotHubNamespace": "[Required]",
        "EndPoint": "messages/events",
        "SharedAccessPolicyName": "[Required]",
        "SharedAccessPolicyKey": null,
        "ConsumerGroupName": "$Default"
    },
    "DataSourceCredentialDomain": null,
    "Serialization": {
        "Type": "Json",
        "Encoding": "UTF8",
        "FieldDelimiter": null
    },
    "PartitionKey": null,
    "CompressionType": "None",
    "ScriptType": "Input"
}